MANIFEST.in
README.md
heartbeat.py
requirements.txt
setup.py
simple_heartbeat.egg-info/PKG-INFO
simple_heartbeat.egg-info/SOURCES.txt
simple_heartbeat.egg-info/dependency_links.txt
simple_heartbeat.egg-info/requires.txt
simple_heartbeat.egg-info/top_level.txt