Metadata-Version: 2.1
Name: simple-heartbeat
Version: 0.1.2
Summary: Simple heartbeat library
Home-page: https://github.com/joshcoales/simple-heartbeat-lib
Author: Joshua Coales
Author-email: dr-spangle@dr-spangle.com
License: MIT
Keywords: heartbeat,monitoring
Platform: UNKNOWN
Classifier: Development Status :: 3 - Alpha
Classifier: Intended Audience :: Developers
Classifier: License :: OSI Approved :: MIT License
Classifier: Operating System :: OS Independent
Classifier: Programming Language :: Python
Classifier: Programming Language :: Python :: 3.6
Classifier: Programming Language :: Python :: 3.7
Classifier: Programming Language :: Python :: 3.8
Classifier: Topic :: Software Development
Classifier: Topic :: Software Development :: Libraries
Classifier: Topic :: Software Development :: Libraries :: Python Modules
